<?xml version="1.0" encoding="UTF-8"?>
<addOn>
  <identifier>e5421f12-4a80-11e4-9553-005056977bd0</identifier>
  <displayType>Function</displayType>
  <translatedDisplayType>
    <en_US>Function</en_US>
    <ja_JP>関数</ja_JP>
    <ko_KR>함수</ko_KR>
    <zh_CN>函数</zh_CN>
  </translatedDisplayType>
  <name>arrow</name>
  <author>Erik Johnson</author>
  <version>2.1</version>
  <downloadUrl>https://www.mathworks.com/matlabcentral/mlc-downloads/downloads/submissions/278/versions/6/download/zip?src=addons_ml_desktop_install&amp;profile_id=9537470</downloadUrl>
  <previewImageUrl>https://www.mathworks.com/responsive_image/160/120/0/0/0/cache/add-ons/image/93dd7e2b3024c396cf42870869edfe65.png</previewImageUrl>
  <installationFolder>Functions</installationFolder>
</addOn>
